fmutool/__init__.py
fmutool/__main__.py
fmutool/__version__.py
fmutool/checker.py
fmutool/cli.py
fmutool/fmu_container.py
fmutool/fmu_operations.py
fmutool/gui.py
fmutool/help.py
fmutool/version.py
fmutool/resources/checkbox-checked-disabled.png
fmutool/resources/checkbox-checked-hover.png
fmutool/resources/checkbox-checked.png
fmutool/resources/checkbox-unchecked-disabled.png
fmutool/resources/checkbox-unchecked-hover.png
fmutool/resources/checkbox-unchecked.png
fmutool/resources/drop_fmu.png
fmutool/resources/fmu.png
fmutool/resources/fmutool.png
fmutool/resources/help.png
fmutool/resources/license.txt
fmutool/resources/model.png
fmutool/resources/fmi-2.0/fmi2Annotation.xsd
fmutool/resources/fmi-2.0/fmi2AttributeGroups.xsd
fmutool/resources/fmi-2.0/fmi2ModelDescription.xsd
fmutool/resources/fmi-2.0/fmi2ScalarVariable.xsd
fmutool/resources/fmi-2.0/fmi2Type.xsd
fmutool/resources/fmi-2.0/fmi2Unit.xsd
fmutool/resources/fmi-2.0/fmi2VariableDependency.xsd
fmutool/resources/linux32/client_sm.so
fmutool/resources/linux32/server_sm
fmutool/resources/linux64/client_sm.so
fmutool/resources/linux64/container.so
fmutool/resources/linux64/server_sm
fmutool/resources/win32/client_sm.dll
fmutool/resources/win32/server_sm.exe
fmutool/resources/win64/client_sm.dll
fmutool/resources/win64/container.dll
fmutool/resources/win64/server_sm.exe
fmutool-1.7.4.1.dist-info/LICENSE.txt
fmutool-1.7.4.1.dist-info/METADATA
fmutool-1.7.4.1.dist-info/WHEEL
fmutool-1.7.4.1.dist-info/entry_points.txt
fmutool-1.7.4.1.dist-info/top_level.txt
fmutool-1.7.4.1.dist-info/RECORD
