Metadata-Version: 2.1
Name: fmutool
Version: 1.7.4.1
Summary: IMPORTANT: this package was renamed 'fmu_manipulation_toolbox'. It won't be updated anymore. Please use those new package.FMUTool is a python application which help to modify a Functional Mock-up Units (FMUs) without recompilation or to group them into FMU Containers
Home-page: https://github.com/grouperenault/fmutool/
Author: Nicolas.LAURENT@Renault.com
Classifier: Development Status :: 7 - Inactive
License-File: LICENSE.txt
Requires-Dist: PyQt5>=5.15.10
Requires-Dist: xmlschema>=3.3.1
Requires-Dist: elementpath>=4.4.0
Requires-Dist: colorama>=0.4.6
Requires-Dist: fmu-manipulation-toolbox==1.7.5
